tourbillon-0.5-py2.7-nspkg.pth
tourbillon/agent/__init__.py
tourbillon/agent/cli.py
tourbillon/agent/plugin_index.json
tourbillon/agent/agent/__init__.py
tourbillon/agent/agent/agent.py
tourbillon/agent/agent2/__init__.py
tourbillon/agent/agent2/agent.py
tourbillon/agent/agent2/agent2.py
tourbillon-0.5.dist-info/DESCRIPTION.rst
tourbillon-0.5.dist-info/METADATA
tourbillon-0.5.dist-info/RECORD
tourbillon-0.5.dist-info/WHEEL
tourbillon-0.5.dist-info/entry_points.txt
tourbillon-0.5.dist-info/metadata.json
tourbillon-0.5.dist-info/namespace_packages.txt
tourbillon-0.5.dist-info/top_level.txt
