Metadata-Version: 2.0
Name: tourbillon
Version: 0.5
Summary: A Python agent for collecting metrics and store them into an InfluxDB.
Home-page: https://github.com/tourbillonpy/tourbillon-agent
Author: The Tourbillon Team
Author-email: tourbillonpy@gmail.com
License: ASF
Keywords: monitoring metrics agent influxdb
Platform: UNKNOWN
Classifier: Development Status :: 4 - Beta
Classifier: Intended Audience :: Developers
Classifier: Intended Audience :: System Administrators
Classifier: License :: OSI Approved :: Apache Software License
Classifier: Operating System :: POSIX :: Linux
Classifier: Programming Language :: Python
Classifier: Programming Language :: Python :: 2.7
Classifier: Programming Language :: Python :: 3.4
Classifier: Programming Language :: Python :: 3.5
Classifier: Topic :: System :: Monitoring
Requires-Dist: click (==5.1)
Requires-Dist: influxdb (>=2.9.1)
Requires-Dist: trollius (==2.0)
